{
  "name": "Blazing Shuriken Dance",
  "sourcePage": "Blazing Shuriken Dance",
  "pageId": 2784,
  "url": "https://naruto.fandom.com/wiki/Blazing_Shuriken_Dance",
  "thumbnail": "https://static.wikia.nocookie.net/naruto/images/5/58/Blazing_Shuriken_Dance.png/revision/latest?cb=20130627125101",
  "raw": {
    "wikitext": "{{Infobox/Jutsu\n|image=Blazing Shuriken Dance.png\n|unnamed jutsu=No\n|game names=Blazing Shuriken Dance\n|parent jutsu=Fire Release: Great Fireball Technique,\n|jutsu classification=Ninjutsu, Shurikenjutsu, Cooperation Ninjutsu\n|jutsu type=Fire Release\n|jutsu class type=Offensive, Defensive\n|jutsu range=Short\n|users=Sakura Haruno~~with~Sasuke Uchiha, Sasuke Uchiha~~with~Sakura Haruno\n|teams=Team 7 (Kakashi)\n|boruto=No\n|debut shippuden=No\n|boruto anime=No\n|game debut=Naruto: Path of the Ninja\n|jutsu media=Game\n}}\nA cooperation technique used by Sasuke and Sakura. Sakura throws a series of [[shuriken]] that have been inflamed by Sasuke's [[Fire Release: Great Fireball Technique]].\n\n== See Also ==\n* [[Fire Release: Phoenix Sage Flower Nail Crimson]]\n\n[[es:Danza Ardiente de Shuriken]]"
  }
}