{
  "name": "Bug Bite",
  "sourcePage": "Bug Bite",
  "pageId": 87506,
  "url": "https://naruto.fandom.com/wiki/Bug_Bite",
  "thumbnail": "https://static.wikia.nocookie.net/naruto/images/5/52/Mushikui.png/revision/latest/scale-to-width-down/600?cb=20130815135249",
  "raw": {
    "wikitext": "{{Infobox/Jutsu\n|ref=<ref name=\"d4\">Fourth Databook, page 326</ref>\n|image=Mushikui.png\n|kanji=蟲食い\n|unnamed jutsu=No\n|romaji=Mushikui\n|literal english=Bug Bite\n|english tv=Bug Bite\n|jutsu classification=Hiden, Taijutsu\n|jutsu class type=Offensive\n|jutsu range=Short\n|users=Fū, Chōmei<!-- Do not remove Chōmei, the Fourth Databook implied that it is a user -->\n|debut manga=566\n|boruto=No\n|debut anime=325\n|debut shippuden=Yes\n|boruto anime=No\n|jutsu media=Anime, Manga\n}}\nWhile in her [[Version 2|transformed]] state, Fū attacks the enemy with a powerful glancing blow as a kick, seemingly biting them in the process.\n\n== References ==\n<references/>\n\n[[es:Picadura]]\n[[fr:Piqûre d'Insecte]]\n[[ka:ხოჭოს ნაკბენი]]\n[[pl:Mushikui]]\n[[pt-br:Mordida de Inseto]]"
  }
}