{
  "name": "Chain Rope",
  "sourcePage": "Chain Rope",
  "pageId": 121052,
  "url": "https://naruto.fandom.com/wiki/Chain_Rope",
  "thumbnail": null,
  "raw": {
    "wikitext": "{{Infobox/Jutsu\n|kanji=鎖縄\n|unnamed jutsu=No\n|romaji=Kusarinawa\n|literal english=Chain Rope\n|parent jutsu=Kamui\n|jutsu classification=Kekkei Genkai~Mangekyō Sharingan, Ninjutsu, Space–Time Ninjutsu, Dōjutsu, Taijutsu, Bukijutsu\n|jutsu class type=Offensive\n|jutsu range=Short\n|users=Obito Uchiha\n|debut shippuden=No\n|game debut=Naruto Shippūden: Ultimate Ninja Storm Generations\n|jutsu media=Game\n}}\nObito lands a couple physical attacks, warps behind his opponent to deliver an upwards kunai slash, throws them up in the air with his chains, and once again warps behind them to deliver an upwards spinning kick."
  }
}