{
  "name": "Crystal: Giant Hexagonal Shuriken",
  "sourcePage": "Crystal: Giant Hexagonal Shuriken",
  "pageId": 12145,
  "url": "https://naruto.fandom.com/wiki/Crystal:_Giant_Hexagonal_Shuriken",
  "thumbnail": "https://static.wikia.nocookie.net/naruto/images/e/e7/Giant_Hexagonal_Shuriken.png/revision/latest/scale-to-width-down/600?cb=20151016013727",
  "raw": {
    "wikitext": "{{Infobox/Jutsu\n|image=Giant Hexagonal Shuriken.png\n|kanji=結晶・巨大六角手裏剣\n|unnamed jutsu=No\n|romaji=Kesshō: Kyodai Rokkaku Shuriken\n|literal english=Crystal: Giant Hexagonal Hidden Hand Blade\n|english tv=Giant Crystal Hexagonal Shuriken\n|jutsu classification=Kekkei Genkai~Crystal Release, Ninjutsu\n|jutsu type=Crystal Release\n|jutsu class type=Offensive\n|jutsu range=Short, Mid, Long\n|users=Guren\n|hand signs=Seal of Confrontation\n|boruto=No\n|sasuke retsuden=No\n|konoha shinden=No\n|debut anime=99\n|debut shippuden=Yes\n|boruto anime=No\n|game debut=Naruto Mobile\n|jutsu media=Anime, Game\n}}\nGuren creates a giant jade-green crystal [[shuriken]], resembling a snowflake, and throws it at the enemy. Despite its sharpness, it wasn't able to penetrate the [[Three-Tails]]' shell.\n\n[[es:Elemento Cristal: Shuriken Hexagonal Gigante]]\n[[fr:Shôton - Shuriken Géant de Cristal]]\n[[pl:Kesshō: Kyodai Rokkaku Shuriken]]\n[[pt-br:Cristal: Shuriken Gigante Hexagonal]]"
  }
}