{
  "name": "Dummy Balloon",
  "sourcePage": "Dummy Balloon",
  "pageId": 128721,
  "url": "https://naruto.fandom.com/wiki/Dummy_Balloon",
  "thumbnail": "https://static.wikia.nocookie.net/naruto/images/f/f6/Dummy_Balloon.png/revision/latest/scale-to-width-down/600?cb=20160428051349",
  "raw": {
    "wikitext": "{{Infobox/Jutsu\n|image=Dummy Balloon.png\n|kanji=ダミーバルーン\n|unnamed jutsu=No\n|romaji=Damībarūn\n|literal english=Dummy Balloon\n|jutsu classification=Ninjutsu\n|jutsu class type=Offensive\n|jutsu range=Short\n|users=Mecha-Naruto\n|debut shippuden=No\n|game debut=Naruto Shippūden: Ultimate Ninja Storm Revolution\n|jutsu media=Game\n}}\n[[Mecha-Naruto]] releases three dummy balloons of himself, that explode upon contact with the opponent."
  }
}