{
  "name": "Fire Release: Blazing Meteors",
  "sourcePage": "Fire Release: Blazing Meteors",
  "pageId": 254162,
  "url": "https://naruto.fandom.com/wiki/Fire_Release:_Blazing_Meteors",
  "thumbnail": "https://static.wikia.nocookie.net/naruto/images/8/8d/Fire_Release_Blazing_Meteors.png/revision/latest/scale-to-width-down/600?cb=20210813131353",
  "raw": {
    "wikitext": "{{Infobox/Jutsu\n|image=Fire Release Blazing Meteors.png\n|kanji=火遁・焔流星\n|unnamed jutsu=No\n|romaji=Katon: Homuranagase\n|literal english=Fire Release: Blazing Meteors\n|viz manga=Fire Style: Flaming Meteors\n|jutsu classification=Ninjutsu,\n|jutsu type=Fire Release\n|jutsu class type=Offensive\n|jutsu range=Short, Mid\n|users=Konohamaru Sarutobi\n|debut manga=21\n|boruto=Yes\n|sasuke retsuden=No\n|konoha shinden=No\n|blue vortex=No\n|debut anime=186\n|debut shippuden=No\n|boruto anime=Yes\n|game debut=Naruto to Boruto: Shinobi Striker\n|jutsu media=Anime, Manga, Game\n}}\nThe user creates a myriad of small fireballs that are then directed towards the target.\n\n== See Also ==\n* [[Fire Release: Phoenix Sage Fire Technique]]\n\n[[fr:Katon - Météores de Feu]]\n[[id:Katon: Homuranagase]]\n[[pl:Katon: Homuranagase]]\n[[ru:Стихия Огня: Пылающие Метеоры]]"
  }
}