{
  "name": "Forbidden Technique: Impure World Seal Destruction",
  "sourcePage": "Forbidden Technique: Impure World Seal Destruction",
  "pageId": 14657,
  "url": "https://naruto.fandom.com/wiki/Forbidden_Technique:_Impure_World_Seal_Destruction",
  "thumbnail": "https://static.wikia.nocookie.net/naruto/images/c/c0/Seal_Destruction1.png/revision/latest?cb=20120705020009",
  "raw": {
    "wikitext": "{{Infobox/Jutsu\n|image=Seal Destruction1.png\nSeal Destruction2.png\nSeal Destruction3.png\nSeal Destruction4.png\n|kanji=禁術・穢土封滅\n|unnamed jutsu=No\n|romaji=Kinjutsu: Edo Fūmetsu\n|literal english=Forbidden Technique: Impure World Seal Destruction\n|game names=Forbidden Jutsu: Seal Destruction\n|parent jutsu=Summoning: Impure World Reincarnation\n|jutsu classification=Ninjutsu, Kinjutsu, Space–Time Ninjutsu, Fūinjutsu\n|jutsu class type=Offensive\n|jutsu range=Short, Mid, Long\n|users=Orochimaru\n|boruto=No\n|sasuke retsuden=No\n|konoha shinden=No\n|debut shippuden=No\n|boruto anime=No\n|game debut=Naruto: Ultimate Ninja 3\n|jutsu media=Game\n}}\nOrochimaru summons a coffin like the one used in the [[Summoning: Impure World Reincarnation]] technique. Ghostly hands come out of the coffin, extending through the body of the opponent, damaging them, until a larger hand grasps them, crushes them, and pulls them into the ethereal dark void within the coffin. The lid closes on the coffin and begins to sink into the darkness surrounding it. Orochimaru laughs sinisterly, watching as it vanishes.\n\n== Trivia ==\n* This technique is a nod to [[wikipedia:CyberConnect2|CyberConnect2]]'s other game series, [[wikipedia:.hack//G.U.|''.hack//G.U.'']]\n\n[[de:Edo Fumetsu]]\n[[es:Jutsu Prohibido: Mundo Puro Eterno]]\n[[pt-br:Técnica Proibida: Destruição do Selo das Terras Impuras]]\n[[pl:Kinjutsu: Edo Fūmetsu]]"
  }
}