{
  "name": "Great Vacuum Cannon",
  "sourcePage": "Great Vacuum Cannon",
  "pageId": 43340,
  "url": "https://naruto.fandom.com/wiki/Great_Vacuum_Cannon",
  "thumbnail": "https://static.wikia.nocookie.net/naruto/images/8/8e/Great_Vacuum_Cannon.png/revision/latest/scale-to-width-down/600?cb=20150216124630",
  "raw": {
    "wikitext": "{{Infobox/Jutsu\n|image=Great Vacuum Cannon.png\n|kanji=豪空砲\n|unnamed jutsu=No\n|romaji=Gōkūhō\n|literal english=Great Vacuum Cannon\n|english tv=Solid Blanks\n|jutsu classification=Ninjutsu, Kenjutsu,\n|jutsu type=Wind Release,\n|jutsu class type=Offensive\n|jutsu range=Short, Mid\n|users=Seimei\n|boruto=No\n|debut anime=219\n|debut shippuden=No\n|boruto anime=No\n|jutsu media=Anime\n}}\nThis technique utilises the [[Takumi Village]]'s special [[Weaknessless Soaring Shortswords]]. The user shoots small, powerful and near-invisible blasts of wind from the blades.\n\n[[pt-br:Grande Canhão de Vácuo]]\n[[fr:Grand Canon à Vide]]\n[[pl:Gōkūhō]]"
  }
}