{
  "name": "Ice Release: One Horned White Whale",
  "sourcePage": "Ice Release: One Horned White Whale",
  "pageId": 6188,
  "url": "https://naruto.fandom.com/wiki/Ice_Release:_One_Horned_White_Whale",
  "thumbnail": "https://static.wikia.nocookie.net/naruto/images/0/0f/Ikkaku_Hakugei.png/revision/latest/scale-to-width-down/600?cb=20140830131906",
  "raw": {
    "wikitext": "{{Infobox/Jutsu\n|image=Ikkaku Hakugei.png\n|kanji=氷遁・一角白鯨\n|unnamed jutsu=No\n|romaji=Hyōton: Ikkaku Hakugei\n|literal english=Ice Release: One Horned White Whale\n|english tv=Ice Style: White Whale Jutsu\n|jutsu classification=Ninjutsu\n|jutsu type=Ice Release\n|jutsu class type=Offensive, Defensive, Supplementary\n|jutsu range=Short, Mid, Long\n|users=Nadare Rōga, Kakashi Hatake~Movie\n|hand signs=Ram, Bird, Monkey, Horse, Snake, Dog\n|debut shippuden=No\n|game debut=Naruto: Ultimate Ninja 2\n|movie debut=Naruto the Movie: Ninja Clash in the Land of Snow\n|jutsu media=Game, Movie\n}}\nThis technique allows the user to create a humongous whale with a long [[Wikipedia:Narwhal|narwhal]] horn out of preexisting ice to attack their opponent. The user needs a source of ice in order to use this technique. The large bulk of this technique is capable of creating great destruction upon landing. However, due to it's size and lack of speed, this technique is used more as a distraction, or to block an opponent's movements rather than attack.\n\n[[es:Elemento Hielo: Ballena Blanca de Un Cuerno]]\n[[pl:Hyōton: Ikkaku Hakugei]]"
  }
}