{
  "name": "Ice Release: Ice Peak Crumbling",
  "sourcePage": "Ice Release: Ice Peak Crumbling",
  "pageId": 109302,
  "url": "https://naruto.fandom.com/wiki/Ice_Release:_Ice_Peak_Crumbling",
  "thumbnail": "https://static.wikia.nocookie.net/naruto/images/9/93/Ice_Peak_Crumbling.png/revision/latest/scale-to-width-down/600?cb=20170806174207",
  "raw": {
    "wikitext": "{{Infobox/Jutsu\n|image=Ice Peak Crumbling.png\n|kanji=氷遁・氷嶽崩\n|unnamed jutsu=No\n|romaji=Hyōton: Hyōgakuhō\n|literal english=Ice Release: Ice Peak Crumbling\n|game names=Ice Style: Iceberg Smasher\n|parent jutsu=Certain-Kill Ice Spears\n|jutsu classification=Kekkei Genkai~Ice Release, Ninjutsu\n|jutsu type=Ice Release\n|jutsu class type=Offensive\n|jutsu range=Short\n|users=Haku\n|debut shippuden=No\n|game debut=Naruto Shippūden: Ultimate Ninja Storm Generations\n|jutsu media=Game\n}}\nHaku creates thin spikes of ice that protrude from the ground underneath the opponent, sending them flying high into the air.\n\n[[es:Elemento Hielo: Colisionador de Iceberg]]"
  }
}