{
  "name": "Leaf Roaring Flame Hurricane",
  "sourcePage": "Leaf Roaring Flame Hurricane",
  "pageId": 91595,
  "url": "https://naruto.fandom.com/wiki/Leaf_Roaring_Flame_Hurricane",
  "thumbnail": "https://static.wikia.nocookie.net/naruto/images/c/c0/Flame_Hurricane1.png/revision/latest/scale-to-width-down/600?cb=20120625205736",
  "raw": {
    "wikitext": "{{Infobox/Jutsu\n|image=Flame Hurricane1.png\nFlame Hurricane2.png\n|kanji=木ノ葉轟炎疾風\n|unnamed jutsu=No\n|romaji=Konoha Gōen Shippū\n|literal english=Tree Leaf Roaring Flame Hurricane\n|game names=Leaf Roaring Blaze Gale\n|parent jutsu=Eight Gates\n|jutsu classification=Kinjutsu, Taijutsu\n|jutsu class type=Offensive\n|jutsu range=Short\n|users=Rock Lee\n|debut shippuden=No\n|game debut=Naruto Shippūden: Ultimate Ninja Impact\n|jutsu media=Game\n}}\nRock Lee unlocks five of the Eight Gates and begins a kick so fast that his leg catches fire. Lee spins around into the air, creating a spiral of flame before bringing his leg down through the centre and into the ground. The fire bursts outwards, blasting any enemy within close proximity.\n\n== See Also ==\n* [[Leaf Hot Wind]]\n* [[Morning Peacock]]\n\n[[es:Rugido Llameante del Huracán de la Hoja]]"
  }
}