{
  "name": "Lightning Release: Thunderstorm",
  "sourcePage": "Lightning Release: Thunderstorm",
  "pageId": 105939,
  "url": "https://naruto.fandom.com/wiki/Lightning_Release:_Thunderstorm",
  "thumbnail": "https://static.wikia.nocookie.net/naruto/images/e/ec/Thunderstorm_Scroll.png/revision/latest/scale-to-width-down/600?cb=20150722102119",
  "raw": {
    "wikitext": "{{Infobox/Jutsu\n|image=Thunderstorm Scroll.png;Preparing for use.\nThunderstorm Sky.png; The sky became cloudy.\n|unnamed jutsu=Yes\n|jutsu classification=Ninjutsu, Cooperation Ninjutsu\n|jutsu type=Lightning Release\n|jutsu class type=Offensive\n|jutsu range=Long\n|debut anime=288\n|debut shippuden=Yes\n|jutsu media=Anime\n}}\nSeveral users gather around a [[scroll]] with the kanji for lightning in it, and gather their [[chakra]]. The kanji begins glowing, and the chakra is sent to the sky, gathering storm clouds, which then unleash lightning.\n\n[[es:Elemento Rayo: Atracción de Rayos]]\n[[fr:Raiton - Orage]]"
  }
}