{
  "name": "Lightning Rat Violent Quake",
  "sourcePage": "Lightning Rat Violent Quake",
  "pageId": 104599,
  "url": "https://naruto.fandom.com/wiki/Lightning_Rat_Violent_Quake",
  "thumbnail": "https://static.wikia.nocookie.net/naruto/images/2/2a/Lightning_Rat_Tremor.png/revision/latest/scale-to-width-down/600?cb=20160226233131",
  "raw": {
    "wikitext": "{{Infobox/Jutsu\n|image=Lightning Rat Tremor.png\n|kanji=雷鼠激震\n|unnamed jutsu=No\n|romaji=Raiso Gekishin\n|literal english=Lightning Rat Violent Quake\n|english tv=Lightning Rat Tremor\n|jutsu classification=Ninjutsu\n|jutsu type=Lightning Release\n|jutsu class type=Offensive\n|jutsu range=Short, Mid, Long\n|users=Nigai\n|hand signs=Monkey, Ox, Boar,Tiger\n|debut anime=286\n|debut shippuden=Yes\n|jutsu media=Anime\n}}\nThe user releases a discharge of electricity that fires several destructive disks of electricity which home in on the targets.\n\n[[es:Ratón Eléctrico Furioso]]\n[[pl:Raiso Gekishin]]"
  }
}