{
  "name": "Mud Release: Mud Doll",
  "sourcePage": "Mud Release: Mud Doll",
  "pageId": 239442,
  "url": "https://naruto.fandom.com/wiki/Mud_Release:_Mud_Doll",
  "thumbnail": null,
  "raw": {
    "wikitext": "{{Infobox/Jutsu\n|kanji=泥遁・泥人形\n|unnamed jutsu=No\n|romaji=Deiton: Doro Ningyō\n|jutsu classification=Kekkei Genkai~Mud Release, Ninjutsu\n|jutsu type=Mud Release\n|users=Ameyuki\n|boruto=No\n|sasuke retsuden=No\n|konoha shinden=No\n|debut shippuden=No\n|boruto anime=No\n|novel debut=Akatsuki Hiden: Evil Flowers in Full Bloom\n|jutsu media=Novel\n}}\nThe user creates one or more humanoid shapes out of mud that carry out their bidding. Like [[sand clone]]s, the mud dolls can recover from most damage they receive. When a mud doll captures an opponent, it can force its hand down their throat, drowning them with mud.\n\n[[pt-br:Estilo Lama: Boneco de Lama]]\n[[pl:Deiton: Doro Ningyō]]"
  }
}