{
  "name": "Pure Land of Paradise",
  "sourcePage": "Pure Land of Paradise",
  "pageId": 64689,
  "url": "https://naruto.fandom.com/wiki/Pure_Land_of_Paradise",
  "thumbnail": "https://static.wikia.nocookie.net/naruto/images/0/0c/Pure_Land_of_Paradise.png/revision/latest/scale-to-width-down/600?cb=20160318204350",
  "raw": {
    "wikitext": "{{Infobox/Jutsu\n|image=Pure Land of Paradise.png\n|kanji=極楽浄土\n|unnamed jutsu=No\n|romaji=Gokuraku Jōdo\n|literal english=Pure Land of Paradise\n|game names=Paradise Pure Land\n|parent jutsu=Chakra Enhanced Strength\n|jutsu classification=Taijutsu\n|jutsu class type=Offensive\n|jutsu range=Short\n|users=Hashirama Senju, Tsunade\n|debut shippuden=No\n|game debut=Naruto Shippūden: Ultimate Ninja Storm 2\n|jutsu media=Game\n}}\nTsunade punches the ground, creating a shockwave that launches her opponent in mid-air. Then using her chakra enhanced strength, she punches the falling opponent in the gut with such force that it sends them flying up into the sky."
  }
}