{
  "name": "Scroll Communication Technique",
  "sourcePage": "Scroll Communication Technique",
  "pageId": 106668,
  "url": "https://naruto.fandom.com/wiki/Scroll_Communication_Technique",
  "thumbnail": "https://static.wikia.nocookie.net/naruto/images/6/6f/Scroll_Communication_Technique_1.png/revision/latest/scale-to-width-down/600?cb=20121220142225",
  "raw": {
    "wikitext": "{{Infobox/Jutsu\n|image=Scroll Communication Technique 1.png;A writing appears on the scroll…\nScroll Communication Technique 2.png;…until it fades away after a few seconds.\n|unnamed jutsu=Yes\n|jutsu classification=Ninjutsu\n|jutsu class type=Supplementary\n|users=Disonasu, Kabuto Yakushi\n|debut anime=291\n|debut shippuden=Yes\n|jutsu media=Anime\n}}\nThe user communicates to another by using a [[scroll]], on which writing appears and disappears.\n\n[[es:Jutsu: Comunicación de Pergamino]]\n[[pt-br:Técnica de Comunicação de Pergaminho]]\n[[ru:Техника Свитка Связи]]"
  }
}