{
  "name": "Umbrella Shock Wave",
  "sourcePage": "Umbrella Shock Wave",
  "pageId": 289835,
  "url": "https://naruto.fandom.com/wiki/Umbrella_Shock_Wave",
  "thumbnail": "https://static.wikia.nocookie.net/naruto/images/6/69/Umbrella_Shock_Wave.png/revision/latest/scale-to-width-down/600?cb=20210307154529",
  "raw": {
    "wikitext": "{{Infobox/Jutsu\n|image=Umbrella Shock Wave.png\n|unnamed jutsu=Yes\n|jutsu classification=Ninjutsu, Bukijutsu\n|jutsu type=Water Release\n|jutsu class type=Offensive, Defensive\n|jutsu range=Short, Mid\n|users=Aoi Rokushō\n|boruto=No\n|sasuke retsuden=No\n|konoha shinden=No\n|debut anime=104\n|debut shippuden=No\n|boruto anime=No\n|jutsu media=Anime\n}}\nAfter swinging his [[umbrella]], Aoi produces a torrent of [[water]] large enough to attack a group of targets. The pressure generated is strong enough to ground his target and crack stone."
  }
}