{
  "name": "Water Release: Hiding in Drizzle Technique",
  "sourcePage": "Water Release: Hiding in Drizzle Technique",
  "pageId": 165417,
  "url": "https://naruto.fandom.com/wiki/Water_Release:_Hiding_in_Drizzle_Technique",
  "thumbnail": "https://static.wikia.nocookie.net/naruto/images/a/a7/Suiren_using_Water_Release.png/revision/latest/scale-to-width-down/600?cb=20150319114519",
  "raw": {
    "wikitext": "{{Infobox/Jutsu\n|image=Suiren using Water Release.png;The user summons drizzle...\nKirisamegakure no Jutsu.png;...to use it as a cover.\n|kanji=水遁・霧雨隠れの術\n|unnamed jutsu=No\n|romaji=Suiton: Kirisamegakure no Jutsu\n|literal english=Water Release: Hiding in Drizzle Technique\n|english tv=Water Style: Hidden Drizzle Jutsu\n|related jutsu=Hiding in Mist Technique\n|jutsu classification=Ninjutsu\n|jutsu type=Water Release\n|jutsu class type=Supplementary\n|users=Suiren\n|hand signs=Seal of Confrontation\n|boruto=No\n|debut anime=404\n|debut shippuden=Yes\n|boruto anime=No\n|jutsu media=Anime\n}}\nThe user generates drizzle to hide themselves and/or their comrades in it. However, the technique is useless in areas with little moisture, as it prevents it from taking effect.\n\n== See Also ==\n* [[Hiding in Frost Technique]]\n* ''[[Water Release: Hiding in Rain Technique]]''"
  }
}