{
  "name": "Wood Pillar Spin Kick",
  "sourcePage": "Wood Pillar Spin Kick",
  "pageId": 94337,
  "url": "https://naruto.fandom.com/wiki/Wood_Pillar_Spin_Kick",
  "thumbnail": "https://static.wikia.nocookie.net/naruto/images/f/f5/Wood_Pillar_Spin_Kick.png/revision/latest/scale-to-width-down/600?cb=20120624065935",
  "raw": {
    "wikitext": "{{Infobox/Jutsu\n|image=Wood Pillar Spin Kick.png\n|unnamed jutsu=No\n|game names=Wood Pillar Spin Kick\n|jutsu classification=Kekkei Genkai~Wood Release, Ninjutsu\n|jutsu type=Wood Release\n|jutsu class type=Offensive, Defensive\n|jutsu range=Short\n|users=Yamato\n|debut shippuden=No\n|game debut=Naruto Shippūden: Ultimate Ninja Heroes 3\n|jutsu media=Game\n}}\n[[Yamato]] makes a pillar of wood come out of the ground, takes hold of the pillar and then begins spinning around with his leg hanging out to kick the opponent multiple times.\n\n\n[[pl:Wirujące Kopnięcie Drewnianego Filaru]]"
  }
}